keras_ocr/__init__.py
keras_ocr/config.py
keras_ocr/data_generation.py
keras_ocr/datasets.py
keras_ocr/detection.py
keras_ocr/evaluation.py
keras_ocr/pipeline.py
keras_ocr/recognition.py
keras_ocr/tools.py
keras_ocr-0.9.3.dist-info/LICENSE
keras_ocr-0.9.3.dist-info/METADATA
keras_ocr-0.9.3.dist-info/WHEEL
keras_ocr-0.9.3.dist-info/RECORD
