Metadata-Version: 2.1
Name: keras-ocr
Version: 0.9.3
Summary: A packaged and flexible version of the CRAFT text detector and Keras CRNN recognition model.
Home-page: https://github.com/faustomorales/keras-ocr
License: MIT
Author: Fausto Morales
Author-email: faustomorales@gmail.com
Requires-Python: >=3.7.5
Classifier: License :: OSI Approved :: MIT License
Classifier: Operating System :: MacOS
Classifier: Operating System :: Microsoft :: Windows
Classifier: Operating System :: POSIX :: Linux
Classifier: Operating System :: Unix
Classifier: Programming Language :: Python :: 3
Classifier: Programming Language :: Python :: 3.8
Classifier: Programming Language :: Python :: 3.9
Classifier: Programming Language :: Python :: 3.10
Classifier: Programming Language :: Python :: 3.11
Classifier: Programming Language :: Python :: 3.12
Classifier: Programming Language :: Python :: 3 :: Only
Requires-Dist: editdistance
Requires-Dist: efficientnet (==1.0.0)
Requires-Dist: essential_generators
Requires-Dist: fonttools
Requires-Dist: imgaug
Requires-Dist: pyclipper
Requires-Dist: shapely
Requires-Dist: tqdm
Requires-Dist: validators
Project-URL: Repository, https://github.com/faustomorales/keras-ocr
